setup.py
meteorpi_model/__init__.py
meteorpi_model.egg-info/PKG-INFO
meteorpi_model.egg-info/SOURCES.txt
meteorpi_model.egg-info/dependency_links.txt
meteorpi_model.egg-info/not-zip-safe
meteorpi_model.egg-info/top_level.txt