Metadata-Version: 1.0
Name: meteorpi-model
Version: 0.1.5
Summary: Model classes used across the MeteorPi project
Home-page: https://github.com/camsci/meteor-pi/
Author: Tom Oinn
Author-email: tomoinn@crypticsquid.com
License: GPL
Platform: UNKNOWN
